places/__init__.py
places/admin.py
places/forms.py
places/managers.py
places/models.py
places/urls.py
places/utils.py
places/views.py
places/locale/fr/LC_MESSAGES/django.mo
places/locale/fr/LC_MESSAGES/django.po
places/migrations/0001_initial.py
places/migrations/0002_picture-and-links.py
places/migrations/0003_country_and_attributes.py
places/migrations/0004_place_status.py
places/migrations/0005_auto_20170420_2129.py
places/migrations/__init__.py
places/south_migrations/0001_initial.py
places/south_migrations/0002_auto__add_category.py
places/south_migrations/0003_auto__add_field_place_category.py
places/south_migrations/__init__.py
places/templates/places/inclusion_tag/staticmap.html
places/templatetags/__init__.py
places/templatetags/places_finder.py
places-0.3.4.dist-info/METADATA
places-0.3.4.dist-info/WHEEL
places-0.3.4.dist-info/top_level.txt
places-0.3.4.dist-info/RECORD
