Metadata-Version: 2.1
Name: places
Version: 0.3.4
Summary: Django project to handle places
Home-page: https://github.com/jibaku/places
Author: Fabien Schwob
Author-email: fabien@x-phuture.com
License: BSD
Platform: UNKNOWN
Classifier: Development Status :: 5 - Production/Stable
Classifier: Environment :: Web Environment
Classifier: Intended Audience :: Developers
Classifier: License :: OSI Approved :: BSD License
Classifier: Operating System :: OS Independent
Classifier: Programming Language :: Python
Classifier: Framework :: Django
